{
	"archive" : {},
	"artifacts" : 
	[
		{
			"path" : "libgoogletest.a"
		}
	],
	"backtrace" : 1,
	"backtraceGraph" : 
	{
		"commands" : 
		[
			"add_library",
			"include_directories"
		],
		"files" : 
		[
			"CMakeLists.txt"
		],
		"nodes" : 
		[
			{
				"file" : 0
			},
			{
				"command" : 0,
				"file" : 0,
				"line" : 40,
				"parent" : 0
			},
			{
				"command" : 1,
				"file" : 0,
				"line" : 16,
				"parent" : 0
			},
			{
				"command" : 1,
				"file" : 0,
				"line" : 26,
				"parent" : 0
			}
		]
	},
	"compileGroups" : 
	[
		{
			"compileCommandFragments" : 
			[
				{
					"fragment" : "-g -arch arm64 -isysroot /Applications/Xcode.app/Contents/Developer/Platforms/MacOSX.platform/Developer/SDKs/MacOSX12.3.sdk -mmacosx-version-min=12.1"
				},
				{
					"fragment" : "-std=gnu++14"
				}
			],
			"includes" : 
			[
				{
					"backtrace" : 2,
					"path" : "/Users/zukhrabasakhanov/CLionProjects/untitled/src"
				},
				{
					"backtrace" : 3,
					"path" : "/Users/zukhrabasakhanov/CLionProjects/untitled/gtest/googletest"
				},
				{
					"backtrace" : 3,
					"path" : "/Users/zukhrabasakhanov/CLionProjects/untitled/gtest/googletest/include"
				}
			],
			"language" : "CXX",
			"languageStandard" : 
			{
				"backtraces" : 
				[
					1
				],
				"standard" : "14"
			},
			"sourceIndexes" : 
			[
				0,
				1
			]
		}
	],
	"id" : "googletest::@6890427a1f51a3e7e1df",
	"name" : "googletest",
	"nameOnDisk" : "libgoogletest.a",
	"paths" : 
	{
		"build" : ".",
		"source" : "."
	},
	"sourceGroups" : 
	[
		{
			"name" : "Source Files",
			"sourceIndexes" : 
			[
				0,
				1
			]
		}
	],
	"sources" : 
	[
		{
			"backtrace" : 1,
			"compileGroupIndex" : 0,
			"isGenerated" : true,
			"path" : "gtest/googletest/src/gtest-all.cc",
			"sourceGroupIndex" : 0
		},
		{
			"backtrace" : 1,
			"compileGroupIndex" : 0,
			"isGenerated" : true,
			"path" : "gtest/googletest/src/gtest_main.cc",
			"sourceGroupIndex" : 0
		}
	],
	"type" : "STATIC_LIBRARY"
}
